{
    "Sources": [
        {
            "source": "0333+7150",
            "ra_deg": 53.4429828,
            "dec_deg": 71.8425183,
            "epoch_year": null,
            "equinox": null,
            "reference": "EastonH",
            "other_references": null,
            "comments": null
        }
    ],
    "ModeledParameters": [
        {
            "model": "photometric",
            "parameter": "distance_J",
            "value": 25.6,
            "error": null,
            "error_upper": null,
            "error_lower": null,
            "unit": "pc",
            "comments": null,
            "reference": "EastonH"
        },
        {
            "model": "photometric",
            "parameter": "distance_W2",
            "value": 29.4,
            "error": null,
            "error_upper": null,
            "error_lower": null,
            "unit": "pc",
            "comments": null,
            "reference": "EastonH"
        }
    ],
    "Names": [
        {
            "other_name": "0333+7150"
        },
        {
            "other_name": "J033346.31+715033.0"
        },
        {
            "other_name": "stevnbak, Sam Goodman, Arttu Sainio"
        }
    ],
    "Photometry": [
        {
            "band": "H",
            "magnitude": 15.909,
            "magnitude_error": 0.172,
            "magnitude_error_upper": null,
            "magnitude_error_lower": null,
            "telescope": null,
            "epoch": null,
            "comments": null,
            "reference": "2MASS",
            "regime": "nir"
        },
        {
            "band": "J",
            "magnitude": 16.774,
            "magnitude_error": 0.176,
            "magnitude_error_upper": null,
            "magnitude_error_lower": null,
            "telescope": null,
            "epoch": null,
            "comments": null,
            "reference": "2MASS",
            "regime": "nir"
        },
        {
            "band": "K",
            "magnitude": 15.659,
            "magnitude_error": 0.214,
            "magnitude_error_upper": null,
            "magnitude_error_lower": null,
            "telescope": null,
            "epoch": null,
            "comments": null,
            "reference": "2MASS",
            "regime": "nir"
        },
        {
            "band": "W1",
            "magnitude": 14.779,
            "magnitude_error": 0.014,
            "magnitude_error_upper": null,
            "magnitude_error_lower": null,
            "telescope": null,
            "epoch": null,
            "comments": null,
            "reference": "CatWISE2020",
            "regime": "mir"
        },
        {
            "band": "W2",
            "magnitude": 14.167,
            "magnitude_error": 0.014,
            "magnitude_error_upper": null,
            "magnitude_error_lower": null,
            "telescope": null,
            "epoch": null,
            "comments": null,
            "reference": "CatWISE2020",
            "regime": "mir"
        },
        {
            "band": "Y",
            "magnitude": 18.928,
            "magnitude_error": 0.086,
            "magnitude_error_upper": null,
            "magnitude_error_lower": null,
            "telescope": null,
            "epoch": null,
            "comments": null,
            "reference": "PS1",
            "regime": "nir"
        }
    ],
    "ProperMotions": [
        {
            "pm_ra": 55.2,
            "pm_ra_error": 5.6,
            "pm_ra_error_upper": null,
            "pm_ra_error_lower": null,
            "pm_dec": -201.7,
            "pm_dec_error": 5.6,
            "pm_dec_error_upper": null,
            "pm_dec_error_lower": null,
            "pm_total": 209.1,
            "v_tan": 29.1,
            "adopted": true,
            "comments": null,
            "reference": "unTimely (Adam)"
        }
    ],
    "SourceTypes": [
        {
            "source_type": "T0",
            "spectral_type_error": 1.0,
            "spectral_type_number": 20.0,
            "comments": null,
            "adopted": true,
            "reference": "EastonH"
        },
        {
            "source_type": "d",
            "spectral_type_error": null,
            "spectral_type_number": null,
            "comments": null,
            "adopted": null,
            "reference": "EastonH"
        }
    ],
    "Spectra": [
        {
            "access_url": null,
            "original_spectrum": null,
            "local_spectrum": null,
            "regime": "nir",
            "telescope": "APO",
            "instrument": "TripleSpec",
            "mode": "Prism",
            "observation_date": "2018-12-19T00:00:00",
            "comments": "Katelyn",
            "reference": "EastonH",
            "other_references": null
        }
    ]
}