{
    "Sources": [
        {
            "source": "0540+1410",
            "ra_deg": 85.1786981,
            "dec_deg": 14.1812163,
            "epoch_year": null,
            "equinox": null,
            "reference": "EastonH",
            "other_references": "Azul",
            "comments": "Comment: could be later; Flags: COLOR_OUTLIER"
        }
    ],
    "Associations": [
        {
            "association": "ARG",
            "membership_probability": 12.0,
            "comments": null,
            "adopted": null,
            "reference": "EastonH"
        },
        {
            "association": "CARN",
            "membership_probability": 87.0,
            "comments": null,
            "adopted": null,
            "reference": "EastonH"
        }
    ],
    "ModeledParameters": [
        {
            "model": "BetaSigma",
            "parameter": "bayes_distance",
            "value": 21.3,
            "error": null,
            "error_upper": null,
            "error_lower": null,
            "unit": "pc",
            "comments": null,
            "reference": "EastonH"
        },
        {
            "model": "BetaSigma",
            "parameter": "bayes_prob",
            "value": 83.9,
            "error": null,
            "error_upper": null,
            "error_lower": null,
            "unit": "",
            "comments": null,
            "reference": "EastonH"
        },
        {
            "model": "photometric",
            "parameter": "distance_J",
            "value": 61.2,
            "error": null,
            "error_upper": null,
            "error_lower": null,
            "unit": "pc",
            "comments": null,
            "reference": "EastonH"
        },
        {
            "model": "photometric",
            "parameter": "distance_W2",
            "value": 30.4,
            "error": null,
            "error_upper": null,
            "error_lower": null,
            "unit": "pc",
            "comments": null,
            "reference": "EastonH"
        }
    ],
    "Names": [
        {
            "other_name": "0540+1410"
        },
        {
            "other_name": "Arttu Sainio, Dan, Sam Goodman, Tom Bickle"
        },
        {
            "other_name": "J054042.88+141052.3"
        }
    ],
    "Photometry": [
        {
            "band": "H",
            "magnitude": 16.232,
            "magnitude_error": 0.185,
            "magnitude_error_upper": null,
            "magnitude_error_lower": null,
            "telescope": null,
            "epoch": null,
            "comments": null,
            "reference": "2MASS",
            "regime": "nir"
        },
        {
            "band": "J",
            "magnitude": 18.027,
            "magnitude_error": 0.052,
            "magnitude_error_upper": null,
            "magnitude_error_lower": null,
            "telescope": null,
            "epoch": null,
            "comments": null,
            "reference": "UHS DR3",
            "regime": "nir"
        },
        {
            "band": "K",
            "magnitude": 15.468,
            "magnitude_error": 0.022,
            "magnitude_error_upper": null,
            "magnitude_error_lower": null,
            "telescope": null,
            "epoch": null,
            "comments": null,
            "reference": "UHS DR3",
            "regime": "nir"
        },
        {
            "band": "W1",
            "magnitude": 14.302,
            "magnitude_error": 0.016,
            "magnitude_error_upper": null,
            "magnitude_error_lower": null,
            "telescope": null,
            "epoch": null,
            "comments": null,
            "reference": "CatWISE2020",
            "regime": "mir"
        },
        {
            "band": "W2",
            "magnitude": 13.659,
            "magnitude_error": 0.014,
            "magnitude_error_upper": null,
            "magnitude_error_lower": null,
            "telescope": null,
            "epoch": null,
            "comments": null,
            "reference": "CatWISE2020",
            "regime": "mir"
        }
    ],
    "ProperMotions": [
        {
            "pm_ra": 25.4,
            "pm_ra_error": 5.6,
            "pm_ra_error_upper": null,
            "pm_ra_error_lower": null,
            "pm_dec": -70.2,
            "pm_dec_error": 5.6,
            "pm_dec_error_upper": null,
            "pm_dec_error_lower": null,
            "pm_total": 74.7,
            "v_tan": 10.8,
            "adopted": true,
            "comments": null,
            "reference": "UHS DR3"
        }
    ],
    "SourceTypes": [
        {
            "source_type": "L6beta",
            "spectral_type_error": 2.0,
            "spectral_type_number": 16.0,
            "comments": null,
            "adopted": true,
            "reference": "EastonH"
        },
        {
            "source_type": "y",
            "spectral_type_error": null,
            "spectral_type_number": null,
            "comments": null,
            "adopted": null,
            "reference": "EastonH"
        }
    ],
    "Spectra": [
        {
            "access_url": null,
            "original_spectrum": null,
            "local_spectrum": null,
            "regime": "nir",
            "telescope": "Keck",
            "instrument": "NIRES",
            "mode": "Prism",
            "observation_date": "2023-12-27T00:00:00",
            "comments": "Burgasser",
            "reference": "EastonH",
            "other_references": null
        }
    ]
}