{
    "Sources": [
        {
            "source": "0757-4230",
            "ra_deg": 119.4924311,
            "dec_deg": -42.5021164,
            "epoch_year": null,
            "equinox": null,
            "reference": "JDK23",
            "other_references": "Azul",
            "comments": "Flags: YMG"
        }
    ],
    "Associations": [
        {
            "association": "ARG",
            "membership_probability": 54.0,
            "comments": null,
            "adopted": null,
            "reference": "EastonH"
        },
        {
            "association": "CARN",
            "membership_probability": 45.0,
            "comments": null,
            "adopted": null,
            "reference": "EastonH"
        }
    ],
    "ModeledParameters": [
        {
            "model": "BetaSigma",
            "parameter": "bayes_distance",
            "value": 30.8,
            "error": null,
            "error_upper": null,
            "error_lower": null,
            "unit": "pc",
            "comments": null,
            "reference": "EastonH"
        },
        {
            "model": "BetaSigma",
            "parameter": "bayes_prob",
            "value": 98.7,
            "error": null,
            "error_upper": null,
            "error_lower": null,
            "unit": "",
            "comments": null,
            "reference": "EastonH"
        },
        {
            "model": "photometric",
            "parameter": "distance_J",
            "value": 25.5,
            "error": null,
            "error_upper": null,
            "error_lower": null,
            "unit": "pc",
            "comments": null,
            "reference": "EastonH"
        },
        {
            "model": "photometric",
            "parameter": "distance_W2",
            "value": 22.9,
            "error": null,
            "error_upper": null,
            "error_lower": null,
            "unit": "pc",
            "comments": null,
            "reference": "EastonH"
        }
    ],
    "Names": [
        {
            "other_name": "0757-4230"
        },
        {
            "other_name": "Dan Caselden"
        },
        {
            "other_name": "J075758.18-423007.6"
        }
    ],
    "Photometry": [
        {
            "band": "H",
            "magnitude": 15.848,
            "magnitude_error": 0.148,
            "magnitude_error_upper": null,
            "magnitude_error_lower": null,
            "telescope": null,
            "epoch": null,
            "comments": null,
            "reference": "2MASS",
            "regime": "nir"
        },
        {
            "band": "J",
            "magnitude": 16.474,
            "magnitude_error": 0.016,
            "magnitude_error_upper": null,
            "magnitude_error_lower": null,
            "telescope": null,
            "epoch": null,
            "comments": null,
            "reference": "VHS",
            "regime": "nir"
        },
        {
            "band": "K",
            "magnitude": 14.776,
            "magnitude_error": 0.013,
            "magnitude_error_upper": null,
            "magnitude_error_lower": null,
            "telescope": null,
            "epoch": null,
            "comments": null,
            "reference": "VHS",
            "regime": "nir"
        },
        {
            "band": "W1",
            "magnitude": 13.637,
            "magnitude_error": 0.013,
            "magnitude_error_upper": null,
            "magnitude_error_lower": null,
            "telescope": null,
            "epoch": null,
            "comments": null,
            "reference": "CatWISE2020",
            "regime": "mir"
        },
        {
            "band": "W2",
            "magnitude": 13.262,
            "magnitude_error": 0.01,
            "magnitude_error_upper": null,
            "magnitude_error_lower": null,
            "telescope": null,
            "epoch": null,
            "comments": null,
            "reference": "CatWISE2020",
            "regime": "mir"
        }
    ],
    "ProperMotions": [
        {
            "pm_ra": -109.8,
            "pm_ra_error": 1.9,
            "pm_ra_error_upper": null,
            "pm_ra_error_lower": null,
            "pm_dec": 63.5,
            "pm_dec_error": 1.8,
            "pm_dec_error_upper": null,
            "pm_dec_error_lower": null,
            "pm_total": 126.8,
            "v_tan": 13.8,
            "adopted": true,
            "comments": null,
            "reference": "VHS (Adam)"
        }
    ],
    "SourceTypes": [
        {
            "source_type": "L7.5",
            "spectral_type_error": 1.0,
            "spectral_type_number": 17.5,
            "comments": null,
            "adopted": true,
            "reference": "EastonH"
        },
        {
            "source_type": "d",
            "spectral_type_error": null,
            "spectral_type_number": null,
            "comments": null,
            "adopted": null,
            "reference": "EastonH"
        }
    ],
    "Spectra": [
        {
            "access_url": null,
            "original_spectrum": null,
            "local_spectrum": null,
            "regime": "nir",
            "telescope": "SOAR",
            "instrument": "ARCoIRIS",
            "mode": "Prism",
            "observation_date": "2023-03-04T00:00:00",
            "comments": "Schneider",
            "reference": "EastonH",
            "other_references": null
        }
    ]
}